pydantic_openai/__init__.py
pydantic_openai/chat.py
pydantic_openai/common.py
pydantic_openai/completion.py
pydantic_openai/embeddings.py
pydantic_openai/moderation.py
pydantic_openai-0.1.0.dist-info/METADATA
pydantic_openai-0.1.0.dist-info/WHEEL
pydantic_openai-0.1.0.dist-info/licenses/LICENSE
pydantic_openai-0.1.0.dist-info/RECORD
