Metadata-Version: 2.1
Name: pydantic_openai
Version: 0.1.0
Summary: Pydantic models for OpenAI's API
Project-URL: Homepage, https://github.com/stillmatic/pydantic-openai
Project-URL: Bug Tracker, https://github.com/stillmatic/pydantic-openai/issues
Author-email: Chris Hua <hua.christopher@gmail.com>
License-File: LICENSE
Classifier: License :: OSI Approved :: MIT License
Classifier: Operating System :: OS Independent
Classifier: Programming Language :: Python :: 3
Requires-Python: >=3.7
Requires-Dist: pydantic
